[
  {
    "uid": "4398754642",
    "password": "FF2026_H3ZVL_HenTaiZ_APIs_H3ZVL_US",
    "accountId": 14399747415,
    "nickname": "TUANXRVNFW",
    "level": 2,
    "region": "US"
  },
  {
    "uid": "4398756447",
    "password": "FF2026_BVAE2_HenTaiZ_APIs_BVAE2_US",
    "accountId": 14399756045,
    "nickname": "TUANEIUNTJ",
    "level": 2,
    "region": "US"
  },
  {
    "uid": "4398759276",
    "password": "FF2026_USZDN_HenTaiZ_APIs_USZDN_US",
    "accountId": 14399770483,
    "nickname": "TUANDQIDRT",
    "level": 2,
    "region": "US"
  },
  {
    "uid": "4398759961",
    "password": "FF2026_BQPMT_HenTaiZ_APIs_BQPMT_US",
    "accountId": 14399774132,
    "nickname": "TUANBYEJ03",
    "level": 2,
    "region": "US"
  },
  {
    "uid": "4398760727",
    "password": "FF2026_RFWYE_HenTaiZ_APIs_RFWYE_US",
    "accountId": 14399777828,
    "nickname": "TUANBOASGE",
    "level": 2,
    "region": "US"
  },
  {
    "uid": "4398761427",
    "password": "FF2026_5MCLL_HenTaiZ_APIs_5MCLL_US",
    "accountId": 14399781360,
    "nickname": "TUANMIER32",
    "level": 2,
    "region": "US"
  },
  {
    "uid": "4398762151",
    "password": "FF2026_2XRFK_HenTaiZ_APIs_2XRFK_US",
    "accountId": 14399784998,
    "nickname": "TUANOGIVFL",
    "level": 2,
    "region": "US"
  },
  {
    "uid": "4398762970",
    "password": "FF2026_QTDN2_HenTaiZ_APIs_QTDN2_US",
    "accountId": 14399789179,
    "nickname": "TUANGOH5DI",
    "level": 2,
    "region": "US"
  },
  {
    "uid": "4398763937",
    "password": "FF2026_D29AF_HenTaiZ_APIs_D29AF_US",
    "accountId": 14399794469,
    "nickname": "TUANNTCGMZ",
    "level": 2,
    "region": "US"
  },
  {
    "uid": "4398764803",
    "password": "FF2026_J3NFS_HenTaiZ_APIs_J3NFS_US",
    "accountId": 14399798466,
    "nickname": "TUANGB1NWQ",
    "level": 2,
    "region": "US"
  },
  {
    "uid": "4398765658",
    "password": "FF2026_DXDWJ_HenTaiZ_APIs_DXDWJ_US",
    "accountId": 14399802547,
    "nickname": "TUAN5SM8N0",
    "level": 2,
    "region": "US"
  },
  {
    "uid": "4398766510",
    "password": "FF2026_UXIBN_HenTaiZ_APIs_UXIBN_US",
    "accountId": 14399806987,
    "nickname": "TUANUWKDCI",
    "level": 2,
    "region": "US"
  },
  {
    "uid": "4398767356",
    "password": "FF2026_6BNVH_HenTaiZ_APIs_6BNVH_US",
    "accountId": 14399811295,
    "nickname": "TUANDS2WJE",
    "level": 2,
    "region": "US"
  },
  {
    "uid": "4398768201",
    "password": "FF2026_CJVHX_HenTaiZ_APIs_CJVHX_US",
    "accountId": 14399815231,
    "nickname": "TUANSOGVBA",
    "level": 2,
    "region": "US"
  },
  {
    "uid": "4398769062",
    "password": "FF2026_EB7FP_HenTaiZ_APIs_EB7FP_US",
    "accountId": 14399819229,
    "nickname": "TUANGTVUS3",
    "level": 2,
    "region": "US"
  },
  {
    "uid": "4398769824",
    "password": "FF2026_OQ46V_HenTaiZ_APIs_OQ46V_US",
    "accountId": 14399823315,
    "nickname": "TUANO7RJFK",
    "level": 2,
    "region": "US"
  },
  {
    "uid": "4398770624",
    "password": "FF2026_NYXVC_HenTaiZ_APIs_NYXVC_US",
    "accountId": 14399827353,
    "nickname": "TUANZW9QQK",
    "level": 2,
    "region": "US"
  },
  {
    "uid": "4398771606",
    "password": "FF2026_EJDAW_HenTaiZ_APIs_EJDAW_US",
    "accountId": 14399832029,
    "nickname": "TUAN50XU5V",
    "level": 2,
    "region": "US"
  },
  {
    "uid": "4398772439",
    "password": "FF2026_JHGQY_HenTaiZ_APIs_JHGQY_US",
    "accountId": 14399835896,
    "nickname": "TUANDQNJAH",
    "level": 2,
    "region": "US"
  },
  {
    "uid": "4398773204",
    "password": "FF2026_LRWGB_HenTaiZ_APIs_LRWGB_US",
    "accountId": 14399839989,
    "nickname": "TUANUBMHKM",
    "level": 2,
    "region": "US"
  },
  {
    "uid": "4398774067",
    "password": "FF2026_XTCIK_HenTaiZ_APIs_XTCIK_US",
    "accountId": 14399843969,
    "nickname": "TUANNIPYLG",
    "level": 2,
    "region": "US"
  },
  {
    "uid": "4398774820",
    "password": "FF2026_52XJ4_HenTaiZ_APIs_52XJ4_US",
    "accountId": 14399847936,
    "nickname": "TUANWSGABN",
    "level": 2,
    "region": "US"
  },
  {
    "uid": "4398775702",
    "password": "FF2026_KQK2W_HenTaiZ_APIs_KQK2W_US",
    "accountId": 14399852369,
    "nickname": "TUANU1NZEH",
    "level": 2,
    "region": "US"
  },
  {
    "uid": "4398776555",
    "password": "FF2026_TZEJF_HenTaiZ_APIs_TZEJF_US",
    "accountId": 14399856485,
    "nickname": "TUANTTDZ3H",
    "level": 2,
    "region": "US"
  },
  {
    "uid": "4398777528",
    "password": "FF2026_IYRRA_HenTaiZ_APIs_IYRRA_US",
    "accountId": 14399861774,
    "nickname": "TUANGBH5LU",
    "level": 2,
    "region": "US"
  },
  {
    "uid": "4398778383",
    "password": "FF2026_VEYWJ_HenTaiZ_APIs_VEYWJ_US",
    "accountId": 14399866508,
    "nickname": "TUANWHRTLY",
    "level": 2,
    "region": "US"
  },
  {
    "uid": "4398779286",
    "password": "FF2026_FKBJR_HenTaiZ_APIs_FKBJR_US",
    "accountId": 14399870236,
    "nickname": "TUANATYZRD",
    "level": 2,
    "region": "US"
  },
  {
    "uid": "4398780115",
    "password": "FF2026_Q02E7_HenTaiZ_APIs_Q02E7_US",
    "accountId": 14399874307,
    "nickname": "TUANGDUTSF",
    "level": 2,
    "region": "US"
  },
  {
    "uid": "4398780905",
    "password": "FF2026_PTR59_HenTaiZ_APIs_PTR59_US",
    "accountId": 14399878298,
    "nickname": "TUAN0WBEBE",
    "level": 2,
    "region": "US"
  },
  {
    "uid": "4398781729",
    "password": "FF2026_ND3LM_HenTaiZ_APIs_ND3LM_US",
    "accountId": 14399882279,
    "nickname": "TUAN9RGAA6",
    "level": 2,
    "region": "US"
  },
  {
    "uid": "4398782715",
    "password": "FF2026_ZWDBW_HenTaiZ_APIs_ZWDBW_US",
    "accountId": 14399886846,
    "nickname": "TUANUU55SI",
    "level": 2,
    "region": "US"
  },
  {
    "uid": "4398783883",
    "password": "FF2026_B4STS_HenTaiZ_APIs_B4STS_US",
    "accountId": 14399892552,
    "nickname": "TUANPVQMV6",
    "level": 2,
    "region": "US"
  },
  {
    "uid": "4398784794",
    "password": "FF2026_9EJWU_HenTaiZ_APIs_9EJWU_US",
    "accountId": 14399896963,
    "nickname": "TUANVSGDHH",
    "level": 2,
    "region": "US"
  },
  {
    "uid": "4398785669",
    "password": "FF2026_AXFXI_HenTaiZ_APIs_AXFXI_US",
    "accountId": 14399900977,
    "nickname": "TUANMKY6PX",
    "level": 2,
    "region": "US"
  },
  {
    "uid": "4398786702",
    "password": "FF2026_BFJFJ_HenTaiZ_APIs_BFJFJ_US",
    "accountId": 14399905707,
    "nickname": "TUANIY3CPV",
    "level": 2,
    "region": "US"
  },
  {
    "uid": "4398787587",
    "password": "FF2026_GFSLI_HenTaiZ_APIs_GFSLI_US",
    "accountId": 14399909855,
    "nickname": "TUANZWMWXI",
    "level": 2,
    "region": "US"
  },
  {
    "uid": "4398788432",
    "password": "FF2026_EH5FC_HenTaiZ_APIs_EH5FC_US",
    "accountId": 14399913758,
    "nickname": "TUANJZHORS",
    "level": 2,
    "region": "US"
  },
  {
    "uid": "4398789331",
    "password": "FF2026_MPZVT_HenTaiZ_APIs_MPZVT_US",
    "accountId": 14399918475,
    "nickname": "TUAN5XEIVA",
    "level": 2,
    "region": "US"
  },
  {
    "uid": "4398790287",
    "password": "FF2026_SZ3HO_HenTaiZ_APIs_SZ3HO_US",
    "accountId": 14399922885,
    "nickname": "TUANZRHQDL",
    "level": 2,
    "region": "US"
  },
  {
    "uid": "4398791171",
    "password": "FF2026_TMIA8_HenTaiZ_APIs_TMIA8_US",
    "accountId": 14399926756,
    "nickname": "TUANR5QW3U",
    "level": 2,
    "region": "US"
  },
  {
    "uid": "4398792012",
    "password": "FF2026_KSKQB_HenTaiZ_APIs_KSKQB_US",
    "accountId": 14399931378,
    "nickname": "TUANOQJML2",
    "level": 2,
    "region": "US"
  },
  {
    "uid": "4398792955",
    "password": "FF2026_LMG6P_HenTaiZ_APIs_LMG6P_US",
    "accountId": 14399935476,
    "nickname": "TUANGFMCLI",
    "level": 2,
    "region": "US"
  },
  {
    "uid": "4398793705",
    "password": "FF2026_I3B8H_HenTaiZ_APIs_I3B8H_US",
    "accountId": 14399939856,
    "nickname": "TUANRJXKGK",
    "level": 2,
    "region": "US"
  },
  {
    "uid": "4398794816",
    "password": "FF2026_G5REZ_HenTaiZ_APIs_G5REZ_US",
    "accountId": 14399944184,
    "nickname": "TUANLELLB1",
    "level": 2,
    "region": "US"
  },
  {
    "uid": "4398795649",
    "password": "FF2026_LZ3CQ_HenTaiZ_APIs_LZ3CQ_US",
    "accountId": 14399948275,
    "nickname": "TUANPYLE9X",
    "level": 2,
    "region": "US"
  },
  {
    "uid": "4398796620",
    "password": "FF2026_KRQSO_HenTaiZ_APIs_KRQSO_US",
    "accountId": 14399953166,
    "nickname": "TUANX7IGQM",
    "level": 2,
    "region": "US"
  },
  {
    "uid": "4398797523",
    "password": "FF2026_J7IJY_HenTaiZ_APIs_J7IJY_US",
    "accountId": 14399957333,
    "nickname": "TUANHKVHK6",
    "level": 2,
    "region": "US"
  },
  {
    "uid": "4398798463",
    "password": "FF2026_IXACP_HenTaiZ_APIs_IXACP_US",
    "accountId": 14399962069,
    "nickname": "TUANI3LNIV",
    "level": 2,
    "region": "US"
  },
  {
    "uid": "4398799446",
    "password": "FF2026_NWNON_HenTaiZ_APIs_NWNON_US",
    "accountId": 14399966650,
    "nickname": "TUANGTQ4EO",
    "level": 2,
    "region": "US"
  },
  {
    "uid": "4398800471",
    "password": "FF2026_HSO54_HenTaiZ_APIs_HSO54_US",
    "accountId": 14399970905,
    "nickname": "TUANPJQYFO",
    "level": 2,
    "region": "US"
  },
  {
    "uid": "4398801696",
    "password": "FF2026_HL6K8_HenTaiZ_APIs_HL6K8_US",
    "accountId": 14399975875,
    "nickname": "TUAN5YV3WT",
    "level": 2,
    "region": "US"
  },
  {
    "uid": "4398802635",
    "password": "FF2026_HJ6LC_HenTaiZ_APIs_HJ6LC_US",
    "accountId": 14399980380,
    "nickname": "TUANGGVFG4",
    "level": 2,
    "region": "US"
  },
  {
    "uid": "4398803696",
    "password": "FF2026_WA1FB_HenTaiZ_APIs_WA1FB_US",
    "accountId": 14399985054,
    "nickname": "TUANUAFEJU",
    "level": 2,
    "region": "US"
  },
  {
    "uid": "4398804598",
    "password": "FF2026_0HRQB_HenTaiZ_APIs_0HRQB_US",
    "accountId": 14399989234,
    "nickname": "TUANAZPUQN",
    "level": 2,
    "region": "US"
  },
  {
    "uid": "4398805734",
    "password": "FF2026_2DYTR_HenTaiZ_APIs_2DYTR_US",
    "accountId": 14399994054,
    "nickname": "TUANHVUM5O",
    "level": 2,
    "region": "US"
  },
  {
    "uid": "4398806986",
    "password": "FF2026_TPBKX_HenTaiZ_APIs_TPBKX_US",
    "accountId": 14399998484,
    "nickname": "TUAND9C2XF",
    "level": 2,
    "region": "US"
  },
  {
    "uid": "4398809939",
    "password": "FF2026_HAOKB_HenTaiZ_APIs_HAOKB_US",
    "accountId": 14400010782,
    "nickname": "TUANSQNZLZ",
    "level": 2,
    "region": "US"
  },
  {
    "uid": "4398810852",
    "password": "FF2026_TYVKE_HenTaiZ_APIs_TYVKE_US",
    "accountId": 14400014966,
    "nickname": "TUANSBHOPO",
    "level": 2,
    "region": "US"
  },
  {
    "uid": "4398811738",
    "password": "FF2026_E8GKW_HenTaiZ_APIs_E8GKW_US",
    "accountId": 14400019453,
    "nickname": "TUANZR4ALH",
    "level": 2,
    "region": "US"
  },
  {
    "uid": "4398812593",
    "password": "FF2026_3ELU0_HenTaiZ_APIs_3ELU0_US",
    "accountId": 14400023321,
    "nickname": "TUANPJ5URF",
    "level": 2,
    "region": "US"
  },
  {
    "uid": "4398813448",
    "password": "FF2026_HLDDS_HenTaiZ_APIs_HLDDS_US",
    "accountId": 14400027579,
    "nickname": "TUANMI9PK4",
    "level": 2,
    "region": "US"
  },
  {
    "uid": "4398814278",
    "password": "FF2026_JQ0XY_HenTaiZ_APIs_JQ0XY_US",
    "accountId": 14400031677,
    "nickname": "TUANF2CSKJ",
    "level": 2,
    "region": "US"
  },
  {
    "uid": "4398815117",
    "password": "FF2026_E2C6I_HenTaiZ_APIs_E2C6I_US",
    "accountId": 14400035457,
    "nickname": "TUANGYPQZY",
    "level": 2,
    "region": "US"
  },
  {
    "uid": "4398815936",
    "password": "FF2026_XEVRM_HenTaiZ_APIs_XEVRM_US",
    "accountId": 14400039770,
    "nickname": "TUANKQR7IC",
    "level": 2,
    "region": "US"
  },
  {
    "uid": "4398816787",
    "password": "FF2026_FT67U_HenTaiZ_APIs_FT67U_US",
    "accountId": 14400043769,
    "nickname": "TUANVCZXGY",
    "level": 2,
    "region": "US"
  },
  {
    "uid": "4398817568",
    "password": "FF2026_C6EMG_HenTaiZ_APIs_C6EMG_US",
    "accountId": 14400047958,
    "nickname": "TUANYKROMC",
    "level": 2,
    "region": "US"
  },
  {
    "uid": "4398818424",
    "password": "FF2026_T04PN_HenTaiZ_APIs_T04PN_US",
    "accountId": 14400052140,
    "nickname": "TUANUPLCJM",
    "level": 2,
    "region": "US"
  },
  {
    "uid": "4398819251",
    "password": "FF2026_U9Q2J_HenTaiZ_APIs_U9Q2J_US",
    "accountId": 14400056123,
    "nickname": "TUANHJ245P",
    "level": 2,
    "region": "US"
  },
  {
    "uid": "4398820116",
    "password": "FF2026_2XX9C_HenTaiZ_APIs_2XX9C_US",
    "accountId": 14400060443,
    "nickname": "TUANSV9Z9G",
    "level": 2,
    "region": "US"
  },
  {
    "uid": "4398820961",
    "password": "FF2026_JMVCS_HenTaiZ_APIs_JMVCS_US",
    "accountId": 14400064698,
    "nickname": "TUANPRXTAU",
    "level": 2,
    "region": "US"
  },
  {
    "uid": "4398821898",
    "password": "FF2026_3P0OZ_HenTaiZ_APIs_3P0OZ_US",
    "accountId": 14400069173,
    "nickname": "TUANYYCN1E",
    "level": 2,
    "region": "US"
  },
  {
    "uid": "4398822766",
    "password": "FF2026_UMKTI_HenTaiZ_APIs_UMKTI_US",
    "accountId": 14400073459,
    "nickname": "TUAN3LAJOX",
    "level": 2,
    "region": "US"
  },
  {
    "uid": "4398823644",
    "password": "FF2026_P67XK_HenTaiZ_APIs_P67XK_US",
    "accountId": 14400077876,
    "nickname": "TUAN8NTX19",
    "level": 2,
    "region": "US"
  },
  {
    "uid": "4398824389",
    "password": "FF2026_ALVFX_HenTaiZ_APIs_ALVFX_US",
    "accountId": 14400081656,
    "nickname": "TUAN7MGFLW",
    "level": 2,
    "region": "US"
  },
  {
    "uid": "4398827196",
    "password": "FF2026_O61VY_HenTaiZ_APIs_O61VY_US",
    "accountId": 14400094949,
    "nickname": "TUANERZT46",
    "level": 2,
    "region": "US"
  },
  {
    "uid": "4398830436",
    "password": "FF2026_AEAWI_HenTaiZ_APIs_AEAWI_US",
    "accountId": 14400111652,
    "nickname": "TUANM9OCVL",
    "level": 2,
    "region": "US"
  },
  {
    "uid": "4398871316",
    "password": "FF2026_JOPTP_HenTaiZ_APIs_JOPTP_US",
    "accountId": 14400329039,
    "nickname": "TUAN0QOX53",
    "level": 2,
    "region": "US"
  },
  {
    "uid": "4398872222",
    "password": "FF2026_IOZNV_HenTaiZ_APIs_IOZNV_US",
    "accountId": 14400333432,
    "nickname": "TUANKVXMCC",
    "level": 2,
    "region": "US"
  },
  {
    "uid": "4398872935",
    "password": "FF2026_O8FQN_HenTaiZ_APIs_O8FQN_US",
    "accountId": 14400339723,
    "nickname": "TUANUPZGME",
    "level": 2,
    "region": "US"
  },
  {
    "uid": "4398873997",
    "password": "FF2026_HXJMF_HenTaiZ_APIs_HXJMF_US",
    "accountId": 14400343875,
    "nickname": "TUAN1LCJ7X",
    "level": 2,
    "region": "US"
  },
  {
    "uid": "4398875996",
    "password": "FF2026_AMDCO_HenTaiZ_APIs_AMDCO_US",
    "accountId": 14400354730,
    "nickname": "TUANPS14FV",
    "level": 2,
    "region": "US"
  },
  {
    "uid": "4398877085",
    "password": "FF2026_TJQSF_HenTaiZ_APIs_TJQSF_US",
    "accountId": 14400360550,
    "nickname": "TUANXCLIA8",
    "level": 2,
    "region": "US"
  },
  {
    "uid": "4398878666",
    "password": "FF2026_UTTUY_HenTaiZ_APIs_UTTUY_US",
    "accountId": 14400368712,
    "nickname": "TUANBFY5EY",
    "level": 2,
    "region": "US"
  },
  {
    "uid": "4402656067",
    "password": "$FF2026_OB52_REUYO_HenTaiZ_APIs_REUYO_US",
    "accountId": 14418587907,
    "nickname": "TUANHEI1D2",
    "level": 2,
    "region": "US"
  },
  {
    "uid": "4402656776",
    "password": "$FF2026_OB52_NDPLU_HenTaiZ_APIs_NDPLU_US",
    "accountId": 14418591343,
    "nickname": "TUANZXVD8F",
    "level": 2,
    "region": "US"
  },
  {
    "uid": "4402659196",
    "password": "$FF2026_OB52_6UH0F_HenTaiZ_APIs_6UH0F_US",
    "accountId": 14418602181,
    "nickname": "TUANRGTTGW",
    "level": 2,
    "region": "US"
  },
  {
    "uid": "4402660385",
    "password": "$FF2026_OB52_1RFJB_HenTaiZ_APIs_1RFJB_US",
    "accountId": 14418607333,
    "nickname": "TUANS6FX6H",
    "level": 2,
    "region": "US"
  },
  {
    "uid": "4402661603",
    "password": "$FF2026_OB52_AL4JV_HenTaiZ_APIs_AL4JV_US",
    "accountId": 14418612665,
    "nickname": "TUANQCMRVO",
    "level": 2,
    "region": "US"
  },
  {
    "uid": "4402662761",
    "password": "$FF2026_OB52_R87BG_HenTaiZ_APIs_R87BG_US",
    "accountId": 14418620594,
    "nickname": "TUANRIG42U",
    "level": 2,
    "region": "US"
  },
  {
    "uid": "4402665865",
    "password": "$FF2026_OB52_PD1ZG_HenTaiZ_APIs_PD1ZG_US",
    "accountId": 14418632985,
    "nickname": "TUANF1YVBV",
    "level": 2,
    "region": "US"
  },
  {
    "uid": "4402668543",
    "password": "$FF2026_OB52_0EB1W_HenTaiZ_APIs_0EB1W_US",
    "accountId": 14418644842,
    "nickname": "TUAN6A5CK4",
    "level": 2,
    "region": "US"
  },
  {
    "uid": "4402669706",
    "password": "$FF2026_OB52_NMUQS_HenTaiZ_APIs_NMUQS_US",
    "accountId": 14418650466,
    "nickname": "TUANRRKGGC",
    "level": 2,
    "region": "US"
  },
  {
    "uid": "4402670586",
    "password": "$FF2026_OB52_FJDPO_HenTaiZ_APIs_FJDPO_US",
    "accountId": 14418654169,
    "nickname": "TUAN4NNZNW",
    "level": 2,
    "region": "US"
  },
  {
    "uid": "4402671443",
    "password": "$FF2026_OB52_G29E7_HenTaiZ_APIs_G29E7_US",
    "accountId": 14418658457,
    "nickname": "TUANJUZ9JL",
    "level": 2,
    "region": "US"
  },
  {
    "uid": "4402672845",
    "password": "$FF2026_OB52_8CT7T_HenTaiZ_APIs_8CT7T_US",
    "accountId": 14418664601,
    "nickname": "TUANXRT0CY",
    "level": 2,
    "region": "US"
  },
  {
    "uid": "4402673652",
    "password": "$FF2026_OB52_DQQMZ_HenTaiZ_APIs_DQQMZ_US",
    "accountId": 14418668348,
    "nickname": "TUANTPWGXC",
    "level": 2,
    "region": "US"
  },
  {
    "uid": "4402674483",
    "password": "$FF2026_OB52_1EWGE_HenTaiZ_APIs_1EWGE_US",
    "accountId": 14418672371,
    "nickname": "TUAN1IKPTJ",
    "level": 2,
    "region": "US"
  },
  {
    "uid": "4402675632",
    "password": "$FF2026_OB52_GHMKV_HenTaiZ_APIs_GHMKV_US",
    "accountId": 14418677580,
    "nickname": "TUANGEYDND",
    "level": 2,
    "region": "US"
  },
  {
    "uid": "4402678360",
    "password": "$FF2026_OB52_ZMZIT_HenTaiZ_APIs_ZMZIT_US",
    "accountId": 14418690184,
    "nickname": "TUAN1LTP9Y",
    "level": 2,
    "region": "US"
  },
  {
    "uid": "4402681166",
    "password": "$FF2026_OB52_QTUGY_HenTaiZ_APIs_QTUGY_US",
    "accountId": 14418707291,
    "nickname": "TUANBNNWS1",
    "level": 2,
    "region": "US"
  },
  {
    "uid": "4402684241",
    "password": "$FF2026_OB52_EG6R9_HenTaiZ_APIs_EG6R9_US",
    "accountId": 14418721054,
    "nickname": "TUANG5XUEE",
    "level": 2,
    "region": "US"
  },
  {
    "uid": "4402690709",
    "password": "$FF2026_OB52_2GTCD_HenTaiZ_APIs_2GTCD_US",
    "accountId": 14418748041,
    "nickname": "TUANLNNCEB",
    "level": 2,
    "region": "US"
  },
  {
    "uid": "4402691557",
    "password": "$FF2026_OB52_UN6YJ_HenTaiZ_APIs_UN6YJ_US",
    "accountId": 14418751993,
    "nickname": "TUANZHOVMX",
    "level": 2,
    "region": "US"
  },
  {
    "uid": "4402692638",
    "password": "$FF2026_OB52_ZLMWO_HenTaiZ_APIs_ZLMWO_US",
    "accountId": 14418758333,
    "nickname": "TUANWHCJMM",
    "level": 2,
    "region": "US"
  },
  {
    "uid": "4402694466",
    "password": "$FF2026_OB52_BK0R7_HenTaiZ_APIs_BK0R7_US",
    "accountId": 14418766200,
    "nickname": "TUAN2A2TEZ",
    "level": 2,
    "region": "US"
  },
  {
    "uid": "4402695381",
    "password": "$FF2026_OB52_QJBML_HenTaiZ_APIs_QJBML_US",
    "accountId": 14418770118,
    "nickname": "TUANY2PAAH",
    "level": 2,
    "region": "US"
  },
  {
    "uid": "4402697380",
    "password": "$FF2026_OB52_IDIIF_HenTaiZ_APIs_IDIIF_US",
    "accountId": 14418782422,
    "nickname": "TUANYXICSN",
    "level": 2,
    "region": "US"
  },
  {
    "uid": "4402700285",
    "password": "$FF2026_OB52_GLB9N_HenTaiZ_APIs_GLB9N_US",
    "accountId": 14418793118,
    "nickname": "TUAN8YDYWY",
    "level": 2,
    "region": "US"
  },
  {
    "uid": "4402701569",
    "password": "$FF2026_OB52_G2KC2_HenTaiZ_APIs_G2KC2_US",
    "accountId": 14418798044,
    "nickname": "TUANFFZAXT",
    "level": 2,
    "region": "US"
  },
  {
    "uid": "4402702470",
    "password": "$FF2026_OB52_0DCFZ_HenTaiZ_APIs_0DCFZ_US",
    "accountId": 14418802270,
    "nickname": "TUANIBCYPV",
    "level": 2,
    "region": "US"
  },
  {
    "uid": "4402703457",
    "password": "$FF2026_OB52_EYSJJ_HenTaiZ_APIs_EYSJJ_US",
    "accountId": 14418806922,
    "nickname": "TUANWL0JNB",
    "level": 2,
    "region": "US"
  },
  {
    "uid": "4402704323",
    "password": "$FF2026_OB52_BGNKB_HenTaiZ_APIs_BGNKB_US",
    "accountId": 14418811163,
    "nickname": "TUANCRPKIE",
    "level": 2,
    "region": "US"
  },
  {
    "uid": "4402705087",
    "password": "$FF2026_OB52_WSOSN_HenTaiZ_APIs_WSOSN_US",
    "accountId": 14418814927,
    "nickname": "TUANSWKDBM",
    "level": 2,
    "region": "US"
  },
  {
    "uid": "4402705967",
    "password": "$FF2026_OB52_RTH4Z_HenTaiZ_APIs_RTH4Z_US",
    "accountId": 14418818546,
    "nickname": "TUANXI62Q4",
    "level": 2,
    "region": "US"
  },
  {
    "uid": "4402706818",
    "password": "$FF2026_OB52_XKCLY_HenTaiZ_APIs_XKCLY_US",
    "accountId": 14418822752,
    "nickname": "TUANEHVFPH",
    "level": 2,
    "region": "US"
  },
  {
    "uid": "4402707621",
    "password": "$FF2026_OB52_SI6LD_HenTaiZ_APIs_SI6LD_US",
    "accountId": 14418826428,
    "nickname": "TUANLGGXUR",
    "level": 2,
    "region": "US"
  },
  {
    "uid": "4402708485",
    "password": "$FF2026_OB52_4AAZN_HenTaiZ_APIs_4AAZN_US",
    "accountId": 14418830253,
    "nickname": "TUAN5W0TNT",
    "level": 2,
    "region": "US"
  },
  {
    "uid": "4402709209",
    "password": "$FF2026_OB52_HQJGY_HenTaiZ_APIs_HQJGY_US",
    "accountId": 14418833596,
    "nickname": "TUAN5MZSRJ",
    "level": 2,
    "region": "US"
  },
  {
    "uid": "4402710035",
    "password": "$FF2026_OB52_7CGDE_HenTaiZ_APIs_7CGDE_US",
    "accountId": 14418837390,
    "nickname": "TUANPTUNV4",
    "level": 2,
    "region": "US"
  },
  {
    "uid": "4402712505",
    "password": "$FF2026_OB52_8SHCL_HenTaiZ_APIs_8SHCL_US",
    "accountId": 14418848644,
    "nickname": "TUANWDKYKP",
    "level": 2,
    "region": "US"
  },
  {
    "uid": "4402713356",
    "password": "$FF2026_OB52_4XJB5_HenTaiZ_APIs_4XJB5_US",
    "accountId": 14418852645,
    "nickname": "TUANUSVBPY",
    "level": 2,
    "region": "US"
  },
  {
    "uid": "4402714150",
    "password": "$FF2026_OB52_WG3HZ_HenTaiZ_APIs_WG3HZ_US",
    "accountId": 14418856620,
    "nickname": "TUANRSY6YR",
    "level": 2,
    "region": "US"
  },
  {
    "uid": "4402715116",
    "password": "$FF2026_OB52_6OJTN_HenTaiZ_APIs_6OJTN_US",
    "accountId": 14418860615,
    "nickname": "TUANUKERYP",
    "level": 2,
    "region": "US"
  },
  {
    "uid": "4402715913",
    "password": "$FF2026_OB52_3NGS8_HenTaiZ_APIs_3NGS8_US",
    "accountId": 14418864368,
    "nickname": "TUANNYWDOM",
    "level": 2,
    "region": "US"
  },
  {
    "uid": "4402716769",
    "password": "$FF2026_OB52_HW4XS_HenTaiZ_APIs_HW4XS_US",
    "accountId": 14418868103,
    "nickname": "TUANO9SUQL",
    "level": 2,
    "region": "US"
  },
  {
    "uid": "4402717688",
    "password": "$FF2026_OB52_QXAQZ_HenTaiZ_APIs_QXAQZ_US",
    "accountId": 14418872427,
    "nickname": "TUANOI3MLH",
    "level": 2,
    "region": "US"
  },
  {
    "uid": "4402718449",
    "password": "$FF2026_OB52_GHMLQ_HenTaiZ_APIs_GHMLQ_US",
    "accountId": 14418876220,
    "nickname": "TUANZJDTXQ",
    "level": 2,
    "region": "US"
  },
  {
    "uid": "4402719380",
    "password": "$FF2026_OB52_Y0B2Z_HenTaiZ_APIs_Y0B2Z_US",
    "accountId": 14418880151,
    "nickname": "TUAN8SS68N",
    "level": 2,
    "region": "US"
  },
  {
    "uid": "4402720203",
    "password": "$FF2026_OB52_W2ALC_HenTaiZ_APIs_W2ALC_US",
    "accountId": 14418884158,
    "nickname": "TUANEGNUI0",
    "level": 2,
    "region": "US"
  },
  {
    "uid": "4402721284",
    "password": "$FF2026_OB52_R8F2X_HenTaiZ_APIs_R8F2X_US",
    "accountId": 14418889048,
    "nickname": "TUANQ1NDDO",
    "level": 2,
    "region": "US"
  },
  {
    "uid": "4402722165",
    "password": "$FF2026_OB52_I93EU_HenTaiZ_APIs_I93EU_US",
    "accountId": 14418893241,
    "nickname": "TUANGAZMNC",
    "level": 2,
    "region": "US"
  },
  {
    "uid": "4402723470",
    "password": "$FF2026_OB52_89VUA_HenTaiZ_APIs_89VUA_US",
    "accountId": 14418899257,
    "nickname": "TUANWEWZ7E",
    "level": 2,
    "region": "US"
  },
  {
    "uid": "4402724262",
    "password": "$FF2026_OB52_RKK6J_HenTaiZ_APIs_RKK6J_US",
    "accountId": 14418902866,
    "nickname": "TUANQLH0OK",
    "level": 2,
    "region": "US"
  },
  {
    "uid": "4402725280",
    "password": "$FF2026_OB52_0G3UX_HenTaiZ_APIs_0G3UX_US",
    "accountId": 14418907605,
    "nickname": "TUANKSQVGN",
    "level": 2,
    "region": "US"
  },
  {
    "uid": "4402726291",
    "password": "$FF2026_OB52_88SDQ_HenTaiZ_APIs_88SDQ_US",
    "accountId": 14418911829,
    "nickname": "TUANYPVQIS",
    "level": 2,
    "region": "US"
  },
  {
    "uid": "4402727328",
    "password": "$FF2026_OB52_OIGAQ_HenTaiZ_APIs_OIGAQ_US",
    "accountId": 14418916790,
    "nickname": "TUANUGHGUI",
    "level": 2,
    "region": "US"
  },
  {
    "uid": "4402728308",
    "password": "$FF2026_OB52_M2DK9_HenTaiZ_APIs_M2DK9_US",
    "accountId": 14418921020,
    "nickname": "TUANRJ3PYT",
    "level": 2,
    "region": "US"
  },
  {
    "uid": "4402729227",
    "password": "$FF2026_OB52_DYBRH_HenTaiZ_APIs_DYBRH_US",
    "accountId": 14418925430,
    "nickname": "TUANQ4WQAO",
    "level": 2,
    "region": "US"
  },
  {
    "uid": "4402730088",
    "password": "$FF2026_OB52_KTRFC_HenTaiZ_APIs_KTRFC_US",
    "accountId": 14418929267,
    "nickname": "TUAN0F0OFT",
    "level": 2,
    "region": "US"
  },
  {
    "uid": "4402731064",
    "password": "$FF2026_OB52_LVJ30_HenTaiZ_APIs_LVJ30_US",
    "accountId": 14418933650,
    "nickname": "TUAN2NSSGC",
    "level": 2,
    "region": "US"
  },
  {
    "uid": "4402732071",
    "password": "$FF2026_OB52_UAEIZ_HenTaiZ_APIs_UAEIZ_US",
    "accountId": 14418938520,
    "nickname": "TUANEADFVO",
    "level": 2,
    "region": "US"
  },
  {
    "uid": "4402732979",
    "password": "$FF2026_OB52_LUDQ9_HenTaiZ_APIs_LUDQ9_US",
    "accountId": 14418942358,
    "nickname": "TUANN2PUDN",
    "level": 2,
    "region": "US"
  },
  {
    "uid": "4402734662",
    "password": "$FF2026_OB52_IO5SU_HenTaiZ_APIs_IO5SU_US",
    "accountId": 14418950202,
    "nickname": "TUANK0U6BA",
    "level": 2,
    "region": "US"
  },
  {
    "uid": "4402735554",
    "password": "$FF2026_OB52_ZVS3Y_HenTaiZ_APIs_ZVS3Y_US",
    "accountId": 14418954121,
    "nickname": "TUANK7ZADI",
    "level": 2,
    "region": "US"
  },
  {
    "uid": "4402736485",
    "password": "$FF2026_OB52_JUAWR_HenTaiZ_APIs_JUAWR_US",
    "accountId": 14418958286,
    "nickname": "TUANIZRCRL",
    "level": 2,
    "region": "US"
  },
  {
    "uid": "4402737387",
    "password": "$FF2026_OB52_NEFSC_HenTaiZ_APIs_NEFSC_US",
    "accountId": 14418962202,
    "nickname": "TUANEZ6AWH",
    "level": 2,
    "region": "US"
  },
  {
    "uid": "4402738283",
    "password": "$FF2026_OB52_7PM53_HenTaiZ_APIs_7PM53_US",
    "accountId": 14418966193,
    "nickname": "TUANG5VSLG",
    "level": 2,
    "region": "US"
  },
  {
    "uid": "4402739141",
    "password": "$FF2026_OB52_OGP6M_HenTaiZ_APIs_OGP6M_US",
    "accountId": 14418969988,
    "nickname": "TUANVCCXFL",
    "level": 2,
    "region": "US"
  },
  {
    "uid": "4402740119",
    "password": "$FF2026_OB52_KRTK9_HenTaiZ_APIs_KRTK9_US",
    "accountId": 14418974265,
    "nickname": "TUANYJHSRM",
    "level": 2,
    "region": "US"
  },
  {
    "uid": "4402741022",
    "password": "$FF2026_OB52_JFUZS_HenTaiZ_APIs_JFUZS_US",
    "accountId": 14418979082,
    "nickname": "TUAN3HNCRB",
    "level": 2,
    "region": "US"
  },
  {
    "uid": "4402741965",
    "password": "$FF2026_OB52_0D9JL_HenTaiZ_APIs_0D9JL_US",
    "accountId": 14418983368,
    "nickname": "TUANYFRIJM",
    "level": 2,
    "region": "US"
  },
  {
    "uid": "4402742809",
    "password": "$FF2026_OB52_XVP9P_HenTaiZ_APIs_XVP9P_US",
    "accountId": 14418987597,
    "nickname": "TUANBUDIQA",
    "level": 2,
    "region": "US"
  },
  {
    "uid": "4402743716",
    "password": "$FF2026_OB52_VQNBI_HenTaiZ_APIs_VQNBI_US",
    "accountId": 14418991723,
    "nickname": "TUAN81KEC5",
    "level": 2,
    "region": "US"
  },
  {
    "uid": "4402744604",
    "password": "$FF2026_OB52_4G1GD_HenTaiZ_APIs_4G1GD_US",
    "accountId": 14418995673,
    "nickname": "TUANS9RY4J",
    "level": 2,
    "region": "US"
  },
  {
    "uid": "4402745458",
    "password": "$FF2026_OB52_YDTFE_HenTaiZ_APIs_YDTFE_US",
    "accountId": 14418999676,
    "nickname": "TUANROZGVW",
    "level": 2,
    "region": "US"
  },
  {
    "uid": "4402746401",
    "password": "$FF2026_OB52_FJWWY_HenTaiZ_APIs_FJWWY_US",
    "accountId": 14419003832,
    "nickname": "TUANNLBF8W",
    "level": 2,
    "region": "US"
  },
  {
    "uid": "4402747779",
    "password": "$FF2026_OB52_UHN2G_HenTaiZ_APIs_UHN2G_US",
    "accountId": 14419010039,
    "nickname": "TUANDKTWPA",
    "level": 2,
    "region": "US"
  },
  {
    "uid": "4402749232",
    "password": "$FF2026_OB52_QD8M0_HenTaiZ_APIs_QD8M0_US",
    "accountId": 14419016808,
    "nickname": "TUANLTS5YK",
    "level": 2,
    "region": "US"
  },
  {
    "uid": "4402750234",
    "password": "$FF2026_OB52_P2GTB_HenTaiZ_APIs_P2GTB_US",
    "accountId": 14419021562,
    "nickname": "TUANKRRSMT",
    "level": 2,
    "region": "US"
  },
  {
    "uid": "4402751242",
    "password": "$FF2026_OB52_GMIWT_HenTaiZ_APIs_GMIWT_US",
    "accountId": 14419025944,
    "nickname": "TUANTWH6EB",
    "level": 2,
    "region": "US"
  },
  {
    "uid": "4402752066",
    "password": "$FF2026_OB52_JTTIX_HenTaiZ_APIs_JTTIX_US",
    "accountId": 14419030088,
    "nickname": "TUANLPYQV8",
    "level": 2,
    "region": "US"
  },
  {
    "uid": "4402752978",
    "password": "$FF2026_OB52_TYCGC_HenTaiZ_APIs_TYCGC_US",
    "accountId": 14419034019,
    "nickname": "TUANCRGJ9G",
    "level": 2,
    "region": "US"
  },
  {
    "uid": "4402753854",
    "password": "$FF2026_OB52_TODSG_HenTaiZ_APIs_TODSG_US",
    "accountId": 14419038216,
    "nickname": "TUANOIXAFU",
    "level": 2,
    "region": "US"
  },
  {
    "uid": "4402754704",
    "password": "$FF2026_OB52_E6DYG_HenTaiZ_APIs_E6DYG_US",
    "accountId": 14419042070,
    "nickname": "TUANVYVV53",
    "level": 2,
    "region": "US"
  },
  {
    "uid": "4402755639",
    "password": "$FF2026_OB52_DP2U0_HenTaiZ_APIs_DP2U0_US",
    "accountId": 14419046296,
    "nickname": "TUANF4WEAY",
    "level": 2,
    "region": "US"
  },
  {
    "uid": "4402756548",
    "password": "$FF2026_OB52_LGYVG_HenTaiZ_APIs_LGYVG_US",
    "accountId": 14419050581,
    "nickname": "TUANJBOXVS",
    "level": 2,
    "region": "US"
  },
  {
    "uid": "4402757501",
    "password": "$FF2026_OB52_JP9XF_HenTaiZ_APIs_JP9XF_US",
    "accountId": 14419055335,
    "nickname": "TUAN8SD3GQ",
    "level": 2,
    "region": "US"
  },
  {
    "uid": "4402758358",
    "password": "$FF2026_OB52_0TDXA_HenTaiZ_APIs_0TDXA_US",
    "accountId": 14419059501,
    "nickname": "TUANKACPC0",
    "level": 2,
    "region": "US"
  },
  {
    "uid": "4402759168",
    "password": "$FF2026_OB52_R2LSX_HenTaiZ_APIs_R2LSX_US",
    "accountId": 14419063720,
    "nickname": "TUANUXLYIW",
    "level": 2,
    "region": "US"
  },
  {
    "uid": "4402760081",
    "password": "$FF2026_OB52_SQHBA_HenTaiZ_APIs_SQHBA_US",
    "accountId": 14419068063,
    "nickname": "TUANP9XXGQ",
    "level": 2,
    "region": "US"
  },
  {
    "uid": "4402760891",
    "password": "$FF2026_OB52_0DUTV_HenTaiZ_APIs_0DUTV_US",
    "accountId": 14419072412,
    "nickname": "TUANJSBUPY",
    "level": 2,
    "region": "US"
  },
  {
    "uid": "4402761725",
    "password": "$FF2026_OB52_Q5IEA_HenTaiZ_APIs_Q5IEA_US",
    "accountId": 14419076557,
    "nickname": "TUAN87ZZ6K",
    "level": 2,
    "region": "US"
  },
  {
    "uid": "4402762524",
    "password": "$FF2026_OB52_NZDL7_HenTaiZ_APIs_NZDL7_US",
    "accountId": 14419080809,
    "nickname": "TUANB9V6W4",
    "level": 2,
    "region": "US"
  },
  {
    "uid": "4402763343",
    "password": "$FF2026_OB52_9LCKB_HenTaiZ_APIs_9LCKB_US",
    "accountId": 14419085402,
    "nickname": "TUANKJLWWV",
    "level": 2,
    "region": "US"
  },
  {
    "uid": "4402764421",
    "password": "$FF2026_OB52_JT06V_HenTaiZ_APIs_JT06V_US",
    "accountId": 14419091028,
    "nickname": "TUAN9JVZYG",
    "level": 2,
    "region": "US"
  },
  {
    "uid": "4402765159",
    "password": "$FF2026_OB52_ZQWAC_HenTaiZ_APIs_ZQWAC_US",
    "accountId": 14419095151,
    "nickname": "TUANSV2YNK",
    "level": 2,
    "region": "US"
  },
  {
    "uid": "4402766006",
    "password": "$FF2026_OB52_HUKQL_HenTaiZ_APIs_HUKQL_US",
    "accountId": 14419099088,
    "nickname": "TUANSZ6WSB",
    "level": 2,
    "region": "US"
  },
  {
    "uid": "4402766836",
    "password": "$FF2026_OB52_QMFVQ_HenTaiZ_APIs_QMFVQ_US",
    "accountId": 14419103368,
    "nickname": "TUANI1J2CO",
    "level": 2,
    "region": "US"
  },
  {
    "uid": "4402767639",
    "password": "$FF2026_OB52_MYII6_HenTaiZ_APIs_MYII6_US",
    "accountId": 14419107246,
    "nickname": "TUANXQAGUA",
    "level": 2,
    "region": "US"
  },
  {
    "uid": "4402768460",
    "password": "$FF2026_OB52_ZKEF7_HenTaiZ_APIs_ZKEF7_US",
    "accountId": 14419111529,
    "nickname": "TUANRRCRMB",
    "level": 2,
    "region": "US"
  },
  {
    "uid": "4402769359",
    "password": "$FF2026_OB52_W41KX_HenTaiZ_APIs_W41KX_US",
    "accountId": 14419115826,
    "nickname": "TUANA5RBOV",
    "level": 2,
    "region": "US"
  },
  {
    "uid": "4402770191",
    "password": "$FF2026_OB52_QVNOH_HenTaiZ_APIs_QVNOH_US",
    "accountId": 14419119787,
    "nickname": "TUANVNSKNT",
    "level": 2,
    "region": "US"
  },
  {
    "uid": "4402770997",
    "password": "$FF2026_OB52_XBVYV_HenTaiZ_APIs_XBVYV_US",
    "accountId": 14419123833,
    "nickname": "TUAN6HFU5Q",
    "level": 2,
    "region": "US"
  },
  {
    "uid": "4403520388",
    "password": "$FF2026_OB52_RL9XI_HenTaiZ_APIs_RL9XI_US",
    "accountId": 14422540952,
    "nickname": "Rong_RG0IX4",
    "level": 2,
    "region": "US"
  },
  {
    "uid": "4403525927",
    "password": "$FF2026_OB52_K4D1K_HenTaiZ_APIs_K4D1K_US",
    "accountId": 14422564206,
    "nickname": "Rong_0N0GAG",
    "level": 2,
    "region": "US"
  },
  {
    "uid": "4403526851",
    "password": "$FF2026_OB52_Y9EE0_HenTaiZ_APIs_Y9EE0_US",
    "accountId": 14422567463,
    "nickname": "Rong_GPB0GR",
    "level": 2,
    "region": "US"
  },
  {
    "uid": "4403529080",
    "password": "$FF2026_OB52_ER05U_HenTaiZ_APIs_ER05U_US",
    "accountId": 14422577019,
    "nickname": "Rong_V9OGRR",
    "level": 2,
    "region": "US"
  },
  {
    "uid": "4403530351",
    "password": "$FF2026_OB52_GEHVI_HenTaiZ_APIs_GEHVI_US",
    "accountId": 14422582208,
    "nickname": "Rong_S377HN",
    "level": 2,
    "region": "US"
  },
  {
    "uid": "4403531320",
    "password": "$FF2026_OB52_J4XSY_HenTaiZ_APIs_J4XSY_US",
    "accountId": 14422586478,
    "nickname": "Rong_5P3AGO",
    "level": 2,
    "region": "US"
  }
]
